odoo8_addon_l10n_es_aeat-8.0.1.9.4-py2.7-nspkg.pth
odoo8_addon_l10n_es_aeat-8.0.1.9.4.dist-info/DESCRIPTION.rst
odoo8_addon_l10n_es_aeat-8.0.1.9.4.dist-info/METADATA
odoo8_addon_l10n_es_aeat-8.0.1.9.4.dist-info/RECORD
odoo8_addon_l10n_es_aeat-8.0.1.9.4.dist-info/WHEEL
odoo8_addon_l10n_es_aeat-8.0.1.9.4.dist-info/metadata.json
odoo8_addon_l10n_es_aeat-8.0.1.9.4.dist-info/namespace_packages.txt
odoo8_addon_l10n_es_aeat-8.0.1.9.4.dist-info/top_level.txt
odoo_addons/l10n_es_aeat/README.rst
odoo_addons/l10n_es_aeat/__init__.py
odoo_addons/l10n_es_aeat/__openerp__.py
odoo_addons/l10n_es_aeat/data/aeat_partner.xml
odoo_addons/l10n_es_aeat/data/aeat_sequence_type.xml
odoo_addons/l10n_es_aeat/i18n/bg.po
odoo_addons/l10n_es_aeat/i18n/ca.po
odoo_addons/l10n_es_aeat/i18n/ca_ES.po
odoo_addons/l10n_es_aeat/i18n/cs.po
odoo_addons/l10n_es_aeat/i18n/es.po
odoo_addons/l10n_es_aeat/i18n/es_CO.po
odoo_addons/l10n_es_aeat/i18n/es_CR.po
odoo_addons/l10n_es_aeat/i18n/eu.po
odoo_addons/l10n_es_aeat/i18n/fr.po
odoo_addons/l10n_es_aeat/i18n/gl.po
odoo_addons/l10n_es_aeat/i18n/hr.po
odoo_addons/l10n_es_aeat/i18n/nl.po
odoo_addons/l10n_es_aeat/i18n/pl.po
odoo_addons/l10n_es_aeat/i18n/pt.po
odoo_addons/l10n_es_aeat/i18n/pt_BR.po
odoo_addons/l10n_es_aeat/i18n/ru.po
odoo_addons/l10n_es_aeat/i18n/sl.po
odoo_addons/l10n_es_aeat/i18n/sv.po
odoo_addons/l10n_es_aeat/i18n/tr.po
odoo_addons/l10n_es_aeat/i18n/vi.po
odoo_addons/l10n_es_aeat/migrations/8.0.1.5.0/post-migration.py
odoo_addons/l10n_es_aeat/migrations/8.0.1.5.0/pre-migration.py
odoo_addons/l10n_es_aeat/migrations/8.0.1.6.0/post-migration.py
odoo_addons/l10n_es_aeat/models/__init__.py
odoo_addons/l10n_es_aeat/models/aeat_export_configuration.py
odoo_addons/l10n_es_aeat/models/aeat_report.py
odoo_addons/l10n_es_aeat/models/aeat_report_tax_mapping.py
odoo_addons/l10n_es_aeat/models/aeat_tax_code_mapping.py
odoo_addons/l10n_es_aeat/security/aeat_security.xml
odoo_addons/l10n_es_aeat/security/ir.model.access.csv
odoo_addons/l10n_es_aeat/static/description/icon.png
odoo_addons/l10n_es_aeat/static/description/icon_source.svg
odoo_addons/l10n_es_aeat/tests/__init__.py
odoo_addons/l10n_es_aeat/tests/test_l10n_es_aeat.py
odoo_addons/l10n_es_aeat/views/account_move_line_view.xml
odoo_addons/l10n_es_aeat/views/aeat_export_configuration_view.xml
odoo_addons/l10n_es_aeat/views/aeat_menuitem.xml
