Metadata-Version: 2.0
Name: odoo8-addon-l10n-es-aeat
Version: 8.0.1.9.4
Summary: AEAT Base
Home-page: https://github.com/OCA/l10n-spain
Author: Pexego,Tecnativa,AvanzOSC,Odoo Community Association (OCA)
Author-email: support@odoo-community.org
License: AGPL-3
Platform: UNKNOWN
Classifier: Programming Language :: Python :: 2.7
Classifier: Framework :: Odoo
Classifier: License :: OSI Approved :: GNU Affero General Public License v3
Requires-Dist: odoo (<9.0a,>=8.0a)
Requires-Dist: unidecode
